{
  "schemaVersion": 1,
  "pages": [
    { "slug": "index",                              "path": "/",                                  "title": "ABA Therapy for Kids in Cleveland, Columbus & Salt Lake City",        "template": "custom", "hidden": false, "draft": false },
    { "slug": "about",                              "path": "/about",                             "title": "About On Target ABA — Mission, Story & Meet Our Founder Ilana Gross, BCBA", "template": "custom", "hidden": false, "draft": false },
    { "slug": "our-process",                        "path": "/our-process",                       "title": "Our Process — How ABA Therapy Works at On Target ABA",                "template": "custom", "hidden": false, "draft": false },
    { "slug": "our-services",                       "path": "/our-services",                      "title": "Our Services — ABA Therapy in Cleveland, Columbus & Salt Lake City", "template": "custom", "hidden": false, "draft": false },
    { "slug": "center-based-aba-therapy",           "path": "/center-based-aba-therapy",          "title": "Center-Based ABA Therapy",                                            "template": "custom", "hidden": false, "draft": false },
    { "slug": "in-home-aba-therapy",                "path": "/in-home-aba-therapy",               "title": "In-Home ABA Therapy",                                                 "template": "custom", "hidden": false, "draft": false },
    { "slug": "early-intervention-autism-program", "path": "/early-intervention-autism-program", "title": "Early Intervention Autism Program",                                   "template": "custom", "hidden": false, "draft": false },
    { "slug": "potty-training-program",             "path": "/potty-training-program",            "title": "Potty Training Program",                                              "template": "custom", "hidden": false, "draft": false },
    { "slug": "autism-testing",                     "path": "/autism-testing",                    "title": "Autism Testing with No Waitlist · Salt Lake Valley",                  "template": "custom", "hidden": false, "draft": false },
    { "slug": "locations",                          "path": "/locations",                         "title": "Locations · Utah & Ohio",                                             "template": "custom", "hidden": false, "draft": false },
    { "slug": "murray-utah",                        "path": "/murray-utah",                       "title": "ABA Therapy in Murray, Utah",                                         "template": "custom", "hidden": false, "draft": false },
    { "slug": "mayfield-ohio",                      "path": "/mayfield-ohio",                     "title": "ABA Therapy in Mayfield Village & Cleveland, Ohio",                   "template": "custom", "hidden": false, "draft": false },
    { "slug": "gahanna-ohio",                       "path": "/gahanna-ohio",                      "title": "ABA Therapy in Gahanna & Columbus, Ohio — Airport Center",            "template": "custom", "hidden": false, "draft": false },
    { "slug": "worthington-ohio",                   "path": "/worthington-ohio",                  "title": "ABA Therapy in Worthington & North Columbus, Ohio",                   "template": "custom", "hidden": false, "draft": false },
    { "slug": "insurance",                          "path": "/insurance",                         "title": "Insurance Coverage for ABA Therapy",                                  "template": "custom", "hidden": false, "draft": false },
    { "slug": "faqs",                               "path": "/faqs",                              "title": "FAQs — ABA Therapy & Autism Diagnosis Questions",                     "template": "custom", "hidden": false, "draft": false },
    { "slug": "careers",                            "path": "/careers",                           "title": "Careers — BCBA & RBT Jobs in Ohio & Utah",                            "template": "custom", "hidden": false, "draft": false },
    { "slug": "job-application",                    "path": "/job-application",                   "title": "Job Application",                                                     "template": "custom", "hidden": false, "draft": false },
    { "slug": "employment-application",             "path": "/employment-application",            "title": "Employment Application",                                              "template": "custom", "hidden": false, "draft": false },
    { "slug": "contact",                            "path": "/contact",                           "title": "Contact — Cleveland, Columbus & Salt Lake City",                      "template": "custom", "hidden": false, "draft": false },
    { "slug": "pre-intake-form",                    "path": "/pre-intake-form",                   "title": "Pre-Intake Form — Get Started Today",                                 "template": "custom", "hidden": false, "draft": false },
    { "slug": "aba-therapy-guide",                  "path": "/aba-therapy-guide",                 "title": "Autism and ABA Therapy: Everything You Need to Know",                 "template": "custom", "hidden": false, "draft": false },
    { "slug": "blog",                               "path": "/blog",                              "title": "Blog — ABA Therapy & Autism Resources",                               "template": "custom", "hidden": false, "draft": false },
    { "slug": "thank-you",                          "path": "/thank-you",                         "title": "Thank you",                                                           "template": "custom", "hidden": true,  "draft": false },
    { "slug": "thank-you-confirmation",             "path": "/thank-you-confirmation",            "title": "Thank you — Submission received",                                     "template": "custom", "hidden": true,  "draft": false },
    { "slug": "privacy-policy",                     "path": "/privacy-policy",                    "title": "Privacy Policy",                                                      "template": "custom", "hidden": false, "draft": false },
    { "slug": "terms-of-service",                   "path": "/terms-of-service",                  "title": "Terms of Service",                                                    "template": "custom", "hidden": false, "draft": false },
    { "slug": "cookie-consent",                     "path": "/cookie-consent",                    "title": "Cookie & Privacy Preferences",                                        "template": "custom", "hidden": false, "draft": false },
    { "slug": "disclaimer",                         "path": "/disclaimer",                        "title": "SMS Disclaimer",                                                      "template": "custom", "hidden": false, "draft": false },
    { "slug": "icon-attribution",                   "path": "/icon-attribution",                  "title": "Icon & Image Credits",                                                "template": "custom", "hidden": false, "draft": false }
  ]
}
